deepview_tensorflow/__init__.py
deepview_tensorflow/_sample_datasets.py
deepview_tensorflow/_sample_models.py
deepview_tensorflow/py.typed
deepview_tensorflow/_tensorflow/__init__.py
deepview_tensorflow/_tensorflow/_tensorflow_file_loaders.py
deepview_tensorflow/_tensorflow/_tensorflow_loading.py
deepview_tensorflow/_tensorflow/_tensorflow_protocols.py
deepview_tensorflow/_tensorflow/_tf2_file_loaders.py
deepview_tensorflow/_tensorflow/_tf2_loading.py
deepview_tensorflow/_tensorflow/_tf2_model.py
deepview_tensorflow/samples/__init__.py
deepview_tensorflow/samples/_simple_cnn_keras.py
deepview_tensorflow-3.9.6.dist-info/WHEEL
deepview_tensorflow-3.9.6.dist-info/METADATA
deepview_tensorflow-3.9.6.dist-info/RECORD
